<annotation>
	<folder>images</folder>
	<filename>205.jpg</filename>
	<path>/home/zac/tensorflow/models/images/205.jpg</path>
	<source>
		<database>Unknown</database>
	</source>
	<size>
		<width>1920</width>
		<height>1080</height>
		<depth>3</depth>
	</size>
	<segmented>0</segmented>
	<object>
		<name>target</name>
		<pose>Unspecified</pose>
		<truncated>0</truncated>
		<difficult>0</difficult>
		<bndbox>
			<xmin>153</xmin>
			<ymin>617</ymin>
			<xmax>201</xmax>
			<ymax>654</ymax>
		</bndbox>
	</object>
	<object>
		<name>target</name>
		<pose>Unspecified</pose>
		<truncated>0</truncated>
		<difficult>0</difficult>
		<bndbox>
			<xmin>344</xmin>
			<ymin>615</ymin>
			<xmax>391</xmax>
			<ymax>655</ymax>
		</bndbox>
	</object>
	<object>
		<name>target</name>
		<pose>Unspecified</pose>
		<truncated>0</truncated>
		<difficult>0</difficult>
		<bndbox>
			<xmin>919</xmin>
			<ymin>552</ymin>
			<xmax>936</xmax>
			<ymax>570</ymax>
		</bndbox>
	</object>
	<object>
		<name>target</name>
		<pose>Unspecified</pose>
		<truncated>0</truncated>
		<difficult>0</difficult>
		<bndbox>
			<xmin>962</xmin>
			<ymin>549</ymin>
			<xmax>981</xmax>
			<ymax>567</ymax>
		</bndbox>
	</object>
	<object>
		<name>target</name>
		<pose>Unspecified</pose>
		<truncated>0</truncated>
		<difficult>0</difficult>
		<bndbox>
			<xmin>1006</xmin>
			<ymin>554</ymin>
			<xmax>1018</xmax>
			<ymax>569</ymax>
		</bndbox>
	</object>
</annotation>
